{"law_abbr":"BPräsWahlG","by_section":{"2":{"marker":"§","title":null,"referenced_by":[{"lawId":"bpräswahlg","section":"6","marker":"§","title":null}],"references":[{"lawId":"bpräswahlg","section":"2","marker":"Art","title":null}]},"4":{"marker":"§","title":null,"referenced_by":[{"lawId":"bpräswahlg","section":"6","marker":"§","title":null}],"references":[]},"6":{"marker":"§","title":null,"referenced_by":[],"references":[{"lawId":"bpräswahlg","section":"2","marker":"§","title":null},{"lawId":"bpräswahlg","section":"4","marker":"§","title":null}]}}}