{"law_abbr":"FStrG","by_section":{"1":{"marker":"§","title":"Einteilung der Bundesstraßen des Fernverkehrs","referenced_by":[{"lawId":"fstrg","section":"2","marker":"§","title":"Widmung, Umstufung, Einziehung"},{"lawId":"fstrg","section":"2","marker":"§","title":"Widmung, Umstufung, Einziehung"},{"lawId":"fstrg","section":"2","marker":"§","title":"Widmung, Umstufung, Einziehung"},{"lawId":"fstrg","section":"6","marker":"§","title":"Eigentum und andere Rechte"}],"references":[{"lawId":"fstrg","section":"5","marker":"§","title":"Träger der Straßenbaulast"},{"lawId":"fstrg","section":"5","marker":"§","title":"Träger der Straßenbaulast"},{"lawId":"fstrg","section":"15","marker":"§","title":"Nebenbetriebe an den Bundesautobahnen"}]},"2":{"marker":"§","title":"Widmung, Umstufung, Einziehung","referenced_by":[{"lawId":"fstrg","section":"9","marker":"§","title":"Bauliche Anlagen an Bundesfernstraßen"},{"lawId":"fstrg","section":"9","marker":"§","title":"Bauliche Anlagen an Bundesfernstraßen"},{"lawId":"fstrg","section":"9a","marker":"§","title":"Veränderungssperre, Vorkaufsrecht"},{"lawId":"fstrg","section":"9a","marker":"§","title":"Veränderungssperre, Vorkaufsrecht"},{"lawId":"fstrg","section":"17b","marker":"§","title":"Planfeststellungsbeschluss, Plangenehmigung"},{"lawId":"fstrg","section":"17e","marker":"§","title":"Rechtsbehelfe"}],"references":[{"lawId":"fstrg","section":"18f","marker":"§","title":"Vorzeitige Besitzeinweisung"},{"lawId":"fstrg","section":"1","marker":"§","title":"Einteilung der Bundesstraßen des Fernverkehrs"},{"lawId":"fstrg","section":"1","marker":"§","title":"Einteilung der Bundesstraßen des Fernverkehrs"},{"lawId":"fstrg","section":"1","marker":"§","title":"Einteilung der Bundesstraßen des Fernverkehrs"},{"lawId":"fstrg","section":"74","marker":"§","title":null},{"lawId":"fstrg","section":"17","marker":"§","title":"Erfordernis der Planfeststellung und vorläufige Anordnung"},{"lawId":"fstrg","section":"7","marker":"§","title":"Gemeingebrauch"},{"lawId":"fstrg","section":"8","marker":"§","title":"Sondernutzungen; Verordnungsermächtigung"},{"lawId":"fstrg","section":"6","marker":"§","title":"Eigentum und andere Rechte"}]},"3":{"marker":"§","title":"Straßenbaulast","referenced_by":[{"lawId":"fstrg","section":"17b","marker":"§","title":"Planfeststellungsbeschluss, Plangenehmigung"},{"lawId":"fstrg","section":"24","marker":"§","title":"Übergangs- und Schlussbestimmungen"}],"references":[]},"4":{"marker":"§","title":"Sicherheitsvorschriften","referenced_by":[{"lawId":"fstrg","section":"9","marker":"§","title":"Bauliche Anlagen an Bundesfernstraßen"},{"lawId":"fstrg","section":"15","marker":"§","title":"Nebenbetriebe an den Bundesautobahnen"}],"references":[]},"5":{"marker":"§","title":"Träger der Straßenbaulast","referenced_by":[{"lawId":"fstrg","section":"1","marker":"§","title":"Einteilung der Bundesstraßen des Fernverkehrs"},{"lawId":"fstrg","section":"1","marker":"§","title":"Einteilung der Bundesstraßen des Fernverkehrs"},{"lawId":"fstrg","section":"6","marker":"§","title":"Eigentum und andere Rechte"},{"lawId":"fstrg","section":"21","marker":"§","title":"Verwaltung der Bundesstraßen in den Ortsdurchfahrten"},{"lawId":"fstrg","section":"24","marker":"§","title":"Übergangs- und Schlussbestimmungen"}],"references":[]},"6":{"marker":"§","title":"Eigentum und andere Rechte","referenced_by":[{"lawId":"fstrg","section":"2","marker":"§","title":"Widmung, Umstufung, Einziehung"},{"lawId":"fstrg","section":"17e","marker":"§","title":"Rechtsbehelfe"}],"references":[{"lawId":"fstrg","section":"1","marker":"§","title":"Einteilung der Bundesstraßen des Fernverkehrs"},{"lawId":"fstrg","section":"5","marker":"§","title":"Träger der Straßenbaulast"}]},"7":{"marker":"§","title":"Gemeingebrauch","referenced_by":[{"lawId":"fstrg","section":"2","marker":"§","title":"Widmung, Umstufung, Einziehung"},{"lawId":"fstrg","section":"22","marker":"§","title":"Zuständigkeit; Verordnungsermächtigung"}],"references":[]},"8":{"marker":"§","title":"Sondernutzungen; Verordnungsermächtigung","referenced_by":[{"lawId":"fstrg","section":"2","marker":"§","title":"Widmung, Umstufung, Einziehung"},{"lawId":"fstrg","section":"8a","marker":"§","title":"Straßenanlieger"},{"lawId":"fstrg","section":"8a","marker":"§","title":"Straßenanlieger"},{"lawId":"fstrg","section":"8a","marker":"§","title":"Straßenanlieger"},{"lawId":"fstrg","section":"8a","marker":"§","title":"Straßenanlieger"},{"lawId":"fstrg","section":"8a","marker":"§","title":"Straßenanlieger"},{"lawId":"fstrg","section":"22","marker":"§","title":"Zuständigkeit; Verordnungsermächtigung"},{"lawId":"fstrg","section":"22","marker":"§","title":"Zuständigkeit; Verordnungsermächtigung"},{"lawId":"fstrg","section":"23","marker":"§","title":"Ordnungswidrigkeiten"},{"lawId":"fstrg","section":"23","marker":"§","title":"Ordnungswidrigkeiten"},{"lawId":"fstrg","section":"23","marker":"§","title":"Ordnungswidrigkeiten"},{"lawId":"fstrg","section":"23","marker":"§","title":"Ordnungswidrigkeiten"},{"lawId":"fstrg","section":"23a","marker":"§","title":"Gebühren, Verordnungsermächtigung"},{"lawId":"fstrg","section":"23a","marker":"§","title":"Gebühren, Verordnungsermächtigung"},{"lawId":"fstrg","section":"24","marker":"§","title":"Übergangs- und Schlussbestimmungen"},{"lawId":"fstrg","section":"24","marker":"§","title":"Übergangs- und Schlussbestimmungen"}],"references":[{"lawId":"fstrg","section":"19","marker":"§","title":"Enteignung"}]},"9":{"marker":"§","title":"Bauliche Anlagen an Bundesfernstraßen","referenced_by":[{"lawId":"fstrg","section":"8a","marker":"§","title":"Straßenanlieger"},{"lawId":"fstrg","section":"8a","marker":"§","title":"Straßenanlieger"},{"lawId":"fstrg","section":"17b","marker":"§","title":"Planfeststellungsbeschluss, Plangenehmigung"},{"lawId":"fstrg","section":"23","marker":"§","title":"Ordnungswidrigkeiten"},{"lawId":"fstrg","section":"23","marker":"§","title":"Ordnungswidrigkeiten"},{"lawId":"fstrg","section":"23","marker":"§","title":"Ordnungswidrigkeiten"},{"lawId":"fstrg","section":"23","marker":"§","title":"Ordnungswidrigkeiten"},{"lawId":"fstrg","section":"23","marker":"§","title":"Ordnungswidrigkeiten"},{"lawId":"fstrg","section":"23a","marker":"§","title":"Gebühren, Verordnungsermächtigung"},{"lawId":"fstrg","section":"23a","marker":"§","title":"Gebühren, Verordnungsermächtigung"},{"lawId":"fstrg","section":"24","marker":"§","title":"Übergangs- und Schlussbestimmungen"},{"lawId":"fstrg","section":"24","marker":"§","title":"Übergangs- und Schlussbestimmungen"}],"references":[{"lawId":"fstrg","section":"2","marker":"§","title":"Widmung, Umstufung, Einziehung"},{"lawId":"fstrg","section":"2","marker":"§","title":"Widmung, Umstufung, Einziehung"},{"lawId":"fstrg","section":"4","marker":"§","title":"Sicherheitsvorschriften"}]},"10":{"marker":"§","title":"Schutzwaldungen","referenced_by":[{"lawId":"fstrg","section":"24","marker":"§","title":"Übergangs- und Schlussbestimmungen"}],"references":[]},"11":{"marker":"§","title":"Schutzmaßnahmen","referenced_by":[{"lawId":"fstrg","section":"22","marker":"§","title":"Zuständigkeit; Verordnungsermächtigung"},{"lawId":"fstrg","section":"23","marker":"§","title":"Ordnungswidrigkeiten"},{"lawId":"fstrg","section":"23","marker":"§","title":"Ordnungswidrigkeiten"},{"lawId":"fstrg","section":"24","marker":"§","title":"Übergangs- und Schlussbestimmungen"}],"references":[]},"12":{"marker":"§","title":"Kreuzungen und Einmündungen öffentlicher Straßen","referenced_by":[{"lawId":"fstrg","section":"13","marker":"§","title":"Unterhaltung der Straßenkreuzungen"},{"lawId":"fstrg","section":"13","marker":"§","title":"Unterhaltung der Straßenkreuzungen"},{"lawId":"fstrg","section":"13b","marker":"§","title":"Ermächtigung zu Rechtsverordnungen"}],"references":[]},"13":{"marker":"§","title":"Unterhaltung der Straßenkreuzungen","referenced_by":[{"lawId":"fstrg","section":"13b","marker":"§","title":"Ermächtigung zu Rechtsverordnungen"},{"lawId":"fstrg","section":"13b","marker":"§","title":"Ermächtigung zu Rechtsverordnungen"},{"lawId":"fstrg","section":"24","marker":"§","title":"Übergangs- und Schlussbestimmungen"},{"lawId":"fstrkrv","section":"1","marker":"§","title":"Höhengleiche Kreuzungen"}],"references":[{"lawId":"fstrg","section":"12","marker":"§","title":"Kreuzungen und Einmündungen öffentlicher Straßen"},{"lawId":"fstrg","section":"12","marker":"§","title":"Kreuzungen und Einmündungen öffentlicher Straßen"}]},"15":{"marker":"§","title":"Nebenbetriebe an den Bundesautobahnen","referenced_by":[{"lawId":"fstrg","section":"1","marker":"§","title":"Einteilung der Bundesstraßen des Fernverkehrs"}],"references":[{"lawId":"fstrg","section":"36","marker":"§","title":null},{"lawId":"fstrg","section":"4","marker":"§","title":"Sicherheitsvorschriften"}]},"17":{"marker":"§","title":"Erfordernis der Planfeststellung und vorläufige Anordnung","referenced_by":[{"lawId":"fstrg","section":"2","marker":"§","title":"Widmung, Umstufung, Einziehung"},{"lawId":"fstrg","section":"17a","marker":"§","title":"Anhörungsverfahren"},{"lawId":"fstrg","section":"17a","marker":"§","title":"Anhörungsverfahren"},{"lawId":"fstrg","section":"17b","marker":"§","title":"Planfeststellungsbeschluss, Plangenehmigung"},{"lawId":"fstrg","section":"17e","marker":"§","title":"Rechtsbehelfe"},{"lawId":"fstrg","section":"19","marker":"§","title":"Enteignung"}],"references":[{"lawId":"fstrg","section":"74","marker":"§","title":null}]},"19":{"marker":"§","title":"Enteignung","referenced_by":[{"lawId":"fstrg","section":"8","marker":"§","title":"Sondernutzungen; Verordnungsermächtigung"},{"lawId":"fstrg","section":"9a","marker":"§","title":"Veränderungssperre, Vorkaufsrecht"},{"lawId":"fstrg","section":"17a","marker":"§","title":"Anhörungsverfahren"}],"references":[{"lawId":"fstrg","section":"17","marker":"§","title":"Erfordernis der Planfeststellung und vorläufige Anordnung"},{"lawId":"fstrg","section":"17f","marker":"§","title":"Anlagen der Verkehrsüberwachung, der Unfallhilfe und des"}]},"20":{"marker":"§","title":"Straßenaufsicht","referenced_by":[{"lawId":"fstrg","section":"17g","marker":"§","title":"Veröffentlichung im Internet"}],"references":[]},"21":{"marker":"§","title":"Verwaltung der Bundesstraßen in den Ortsdurchfahrten","referenced_by":[],"references":[{"lawId":"fstrg","section":"5","marker":"§","title":"Träger der Straßenbaulast"}]},"22":{"marker":"§","title":"Zuständigkeit; Verordnungsermächtigung","referenced_by":[{"lawId":"fstrg","section":"23a","marker":"§","title":"Gebühren, Verordnungsermächtigung"},{"lawId":"fstrg","section":"23a","marker":"§","title":"Gebühren, Verordnungsermächtigung"}],"references":[{"lawId":"fstrg","section":"36","marker":"§","title":null},{"lawId":"fstrg","section":"7","marker":"§","title":"Gemeingebrauch"},{"lawId":"fstrg","section":"8","marker":"§","title":"Sondernutzungen; Verordnungsermächtigung"},{"lawId":"fstrg","section":"8","marker":"§","title":"Sondernutzungen; Verordnungsermächtigung"},{"lawId":"fstrg","section":"11","marker":"§","title":"Schutzmaßnahmen"}]},"23":{"marker":"§","title":"Ordnungswidrigkeiten","referenced_by":[{"lawId":"fstrg","section":"17g","marker":"§","title":"Veröffentlichung im Internet"}],"references":[{"lawId":"fstrg","section":"8","marker":"§","title":"Sondernutzungen; Verordnungsermächtigung"},{"lawId":"fstrg","section":"8","marker":"§","title":"Sondernutzungen; Verordnungsermächtigung"},{"lawId":"fstrg","section":"8","marker":"§","title":"Sondernutzungen; Verordnungsermächtigung"},{"lawId":"fstrg","section":"8a","marker":"§","title":"Straßenanlieger"},{"lawId":"fstrg","section":"8a","marker":"§","title":"Straßenanlieger"},{"lawId":"fstrg","section":"8","marker":"§","title":"Sondernutzungen; Verordnungsermächtigung"},{"lawId":"fstrg","section":"8a","marker":"§","title":"Straßenanlieger"},{"lawId":"fstrg","section":"9","marker":"§","title":"Bauliche Anlagen an Bundesfernstraßen"},{"lawId":"fstrg","section":"9","marker":"§","title":"Bauliche Anlagen an Bundesfernstraßen"},{"lawId":"fstrg","section":"9","marker":"§","title":"Bauliche Anlagen an Bundesfernstraßen"},{"lawId":"fstrg","section":"9","marker":"§","title":"Bauliche Anlagen an Bundesfernstraßen"},{"lawId":"fstrg","section":"9","marker":"§","title":"Bauliche Anlagen an Bundesfernstraßen"},{"lawId":"fstrg","section":"9a","marker":"§","title":"Veränderungssperre, Vorkaufsrecht"},{"lawId":"fstrg","section":"11","marker":"§","title":"Schutzmaßnahmen"},{"lawId":"fstrg","section":"11","marker":"§","title":"Schutzmaßnahmen"},{"lawId":"fstrg","section":"16a","marker":"§","title":"Vorarbeiten"},{"lawId":"fstrg","section":"36","marker":"§","title":null}]},"24":{"marker":"§","title":"Übergangs- und Schlussbestimmungen","referenced_by":[],"references":[{"lawId":"fstrg","section":"11","marker":"§","title":"Schutzmaßnahmen"},{"lawId":"fstrg","section":"17c","marker":"§","title":"Rechtswirkungen der Planfeststellung und der Plangenehmigung"},{"lawId":"fstrg","section":"13","marker":"§","title":"Unterhaltung der Straßenkreuzungen"},{"lawId":"fstrg","section":"5","marker":"§","title":"Träger der Straßenbaulast"},{"lawId":"fstrg","section":"9","marker":"§","title":"Bauliche Anlagen an Bundesfernstraßen"},{"lawId":"fstrg","section":"10","marker":"§","title":"Schutzwaldungen"},{"lawId":"fstrg","section":"8","marker":"§","title":"Sondernutzungen; Verordnungsermächtigung"},{"lawId":"fstrg","section":"23a","marker":"§","title":"Gebühren, Verordnungsermächtigung"},{"lawId":"fstrg","section":"8","marker":"§","title":"Sondernutzungen; Verordnungsermächtigung"},{"lawId":"fstrg","section":"9","marker":"§","title":"Bauliche Anlagen an Bundesfernstraßen"},{"lawId":"fstrg","section":"3","marker":"§","title":"Straßenbaulast"}]},"27":{"marker":"§","title":"(Inkrafttreten)","referenced_by":[{"lawId":"fstrg","section":"17b","marker":"§","title":"Planfeststellungsbeschluss, Plangenehmigung"},{"lawId":"fstrg","section":"17b","marker":"§","title":"Planfeststellungsbeschluss, Plangenehmigung"}],"references":[]},"5a":{"marker":"§","title":"Zuwendungen für fremde Träger der Straßenbaulast","referenced_by":[],"references":[{"lawId":"fstrg","section":"46","marker":"§","title":null}]},"8a":{"marker":"§","title":"Straßenanlieger","referenced_by":[{"lawId":"fstrg","section":"19a","marker":"§","title":"Entschädigungsverfahren"},{"lawId":"fstrg","section":"23","marker":"§","title":"Ordnungswidrigkeiten"},{"lawId":"fstrg","section":"23","marker":"§","title":"Ordnungswidrigkeiten"},{"lawId":"fstrg","section":"23","marker":"§","title":"Ordnungswidrigkeiten"}],"references":[{"lawId":"fstrg","section":"8","marker":"§","title":"Sondernutzungen; Verordnungsermächtigung"},{"lawId":"fstrg","section":"8","marker":"§","title":"Sondernutzungen; Verordnungsermächtigung"},{"lawId":"fstrg","section":"9","marker":"§","title":"Bauliche Anlagen an Bundesfernstraßen"},{"lawId":"fstrg","section":"9","marker":"§","title":"Bauliche Anlagen an Bundesfernstraßen"},{"lawId":"fstrg","section":"8","marker":"§","title":"Sondernutzungen; Verordnungsermächtigung"},{"lawId":"fstrg","section":"8","marker":"§","title":"Sondernutzungen; Verordnungsermächtigung"},{"lawId":"fstrg","section":"8","marker":"§","title":"Sondernutzungen; Verordnungsermächtigung"},{"lawId":"fstrg","section":"254","marker":"§","title":null}]},"9a":{"marker":"§","title":"Veränderungssperre, Vorkaufsrecht","referenced_by":[{"lawId":"fstrg","section":"23","marker":"§","title":"Ordnungswidrigkeiten"}],"references":[{"lawId":"fstrg","section":"19","marker":"§","title":"Enteignung"},{"lawId":"fstrg","section":"2","marker":"§","title":"Widmung, Umstufung, Einziehung"},{"lawId":"fstrg","section":"2","marker":"§","title":"Widmung, Umstufung, Einziehung"}]},"12a":{"marker":"§","title":"Kreuzungen mit Gewässern","referenced_by":[{"lawId":"fstrg","section":"13a","marker":"§","title":"Unterhaltung der Kreuzungen mit Gewässern"}],"references":[{"lawId":"fstrg","section":"31","marker":"§","title":null},{"lawId":"fstrg","section":"41","marker":"§","title":null}]},"13a":{"marker":"§","title":"Unterhaltung der Kreuzungen mit Gewässern","referenced_by":[{"lawId":"fstrg","section":"13b","marker":"§","title":"Ermächtigung zu Rechtsverordnungen"}],"references":[{"lawId":"fstrg","section":"12a","marker":"§","title":"Kreuzungen mit Gewässern"},{"lawId":"fstrg","section":"42","marker":"§","title":null}]},"13b":{"marker":"§","title":"Ermächtigung zu Rechtsverordnungen","referenced_by":[],"references":[{"lawId":"fstrg","section":"12","marker":"§","title":"Kreuzungen und Einmündungen öffentlicher Straßen"},{"lawId":"fstrg","section":"13","marker":"§","title":"Unterhaltung der Straßenkreuzungen"},{"lawId":"fstrg","section":"13","marker":"§","title":"Unterhaltung der Straßenkreuzungen"},{"lawId":"fstrg","section":"13a","marker":"§","title":"Unterhaltung der Kreuzungen mit Gewässern"}]},"16a":{"marker":"§","title":"Vorarbeiten","referenced_by":[{"lawId":"fstrg","section":"23","marker":"§","title":"Ordnungswidrigkeiten"}],"references":[]},"17a":{"marker":"§","title":"Anhörungsverfahren","referenced_by":[{"lawId":"fstrg","section":"17b","marker":"§","title":"Planfeststellungsbeschluss, Plangenehmigung"},{"lawId":"fstrg","section":"17g","marker":"§","title":"Veröffentlichung im Internet"}],"references":[{"lawId":"fstrg","section":"73","marker":"§","title":null},{"lawId":"fstrg","section":"17","marker":"§","title":"Erfordernis der Planfeststellung und vorläufige Anordnung"},{"lawId":"fstrg","section":"73","marker":"§","title":null},{"lawId":"fstrg","section":"17","marker":"§","title":"Erfordernis der Planfeststellung und vorläufige Anordnung"},{"lawId":"fstrg","section":"19","marker":"§","title":"Enteignung"},{"lawId":"fstrg","section":"73","marker":"§","title":null},{"lawId":"fstrg","section":"73","marker":"§","title":null},{"lawId":"fstrg","section":"18","marker":"§","title":null},{"lawId":"fstrg","section":"73","marker":"§","title":null},{"lawId":"fstrg","section":"18","marker":"§","title":null},{"lawId":"fstrg","section":"73","marker":"§","title":null},{"lawId":"fstrg","section":"73","marker":"§","title":null},{"lawId":"fstrg","section":"18","marker":"§","title":null}]},"17b":{"marker":"§","title":"Planfeststellungsbeschluss, Plangenehmigung","referenced_by":[{"lawId":"fstrg","section":"17e","marker":"§","title":"Rechtsbehelfe"},{"lawId":"uvpg","section":"21","marker":"§","title":"Äußerungen und Einwendungen der Öffentlichkeit"}],"references":[{"lawId":"fstrg","section":"74","marker":"§","title":null},{"lawId":"fstrg","section":"27","marker":"§","title":"(Inkrafttreten)"},{"lawId":"fstrg","section":"74","marker":"§","title":null},{"lawId":"fstrg","section":"17a","marker":"§","title":"Anhörungsverfahren"},{"lawId":"fstrg","section":"74","marker":"§","title":null},{"lawId":"fstrg","section":"27","marker":"§","title":"(Inkrafttreten)"},{"lawId":"fstrg","section":"74","marker":"§","title":null},{"lawId":"fstrg","section":"2","marker":"§","title":"Widmung, Umstufung, Einziehung"},{"lawId":"fstrg","section":"3","marker":"§","title":"Straßenbaulast"},{"lawId":"fstrg","section":"74","marker":"§","title":null},{"lawId":"fstrg","section":"9","marker":"§","title":"Bauliche Anlagen an Bundesfernstraßen"},{"lawId":"fstrg","section":"17","marker":"§","title":"Erfordernis der Planfeststellung und vorläufige Anordnung"},{"lawId":"fstrg","section":"40","marker":"§","title":null},{"lawId":"fstrg","section":"44","marker":"§","title":null}]},"17c":{"marker":"§","title":"Rechtswirkungen der Planfeststellung und der Plangenehmigung","referenced_by":[{"lawId":"fstrg","section":"24","marker":"§","title":"Übergangs- und Schlussbestimmungen"}],"references":[{"lawId":"fstrg","section":"75","marker":"§","title":null},{"lawId":"fstrg","section":"75","marker":"§","title":null}]},"17d":{"marker":"§","title":"Planänderung vor Fertigstellung des Vorhabens","referenced_by":[],"references":[{"lawId":"fstrg","section":"75","marker":"§","title":null},{"lawId":"fstrg","section":"76","marker":"§","title":null},{"lawId":"fstrg","section":"76","marker":"§","title":null},{"lawId":"fstrg","section":"73","marker":"§","title":null},{"lawId":"fstrg","section":"18","marker":"§","title":null}]},"17e":{"marker":"§","title":"Rechtsbehelfe","referenced_by":[{"lawId":"umwrg","section":"6","marker":"§","title":"Klagebegründungsfrist"}],"references":[{"lawId":"fstrg","section":"50","marker":"§","title":null},{"lawId":"fstrg","section":"17b","marker":"§","title":"Planfeststellungsbeschluss, Plangenehmigung"},{"lawId":"fstrg","section":"74","marker":"§","title":null},{"lawId":"fstrg","section":"17","marker":"§","title":"Erfordernis der Planfeststellung und vorläufige Anordnung"},{"lawId":"fstrg","section":"2","marker":"§","title":"Widmung, Umstufung, Einziehung"},{"lawId":"fstrg","section":"80","marker":"§","title":null},{"lawId":"fstrg","section":"58","marker":"§","title":null},{"lawId":"fstrg","section":"80","marker":"§","title":null},{"lawId":"fstrg","section":"6","marker":"§","title":"Eigentum und andere Rechte"}]},"17f":{"marker":"§","title":"Anlagen der Verkehrsüberwachung, der Unfallhilfe und des","referenced_by":[{"lawId":"fstrg","section":"18f","marker":"§","title":"Vorzeitige Besitzeinweisung"},{"lawId":"fstrg","section":"19","marker":"§","title":"Enteignung"}],"references":[]},"17g":{"marker":"§","title":"Veröffentlichung im Internet","referenced_by":[],"references":[{"lawId":"fstrg","section":"17a","marker":"§","title":"Anhörungsverfahren"},{"lawId":"fstrg","section":"27a","marker":"§","title":null},{"lawId":"fstrg","section":"20","marker":"§","title":"Straßenaufsicht"},{"lawId":"fstrg","section":"23","marker":"§","title":"Ordnungswidrigkeiten"}]},"17i":{"marker":"§","title":"Planfeststellungsverfahren bei Vorhaben im transeuropäischen Verkehrsnetz","referenced_by":[{"lawId":"fstrg","section":"17j","marker":"§","title":"Grenzüberschreitende Vorhaben im transeuropäischen Verkehrsnetz"},{"lawId":"fstrg","section":"17j","marker":"§","title":"Grenzüberschreitende Vorhaben im transeuropäischen Verkehrsnetz"},{"lawId":"fstrg","section":"17k","marker":"§","title":"Berichterstattung an die Europäische Kommission"}],"references":[{"lawId":"fstrg","section":"73","marker":"§","title":null},{"lawId":"fstrg","section":"73","marker":"§","title":null}]},"17j":{"marker":"§","title":"Grenzüberschreitende Vorhaben im transeuropäischen Verkehrsnetz","referenced_by":[{"lawId":"fstrg","section":"17k","marker":"§","title":"Berichterstattung an die Europäische Kommission"}],"references":[{"lawId":"fstrg","section":"17i","marker":"§","title":"Planfeststellungsverfahren bei Vorhaben im transeuropäischen Verkehrsnetz"},{"lawId":"fstrg","section":"17i","marker":"§","title":"Planfeststellungsverfahren bei Vorhaben im transeuropäischen Verkehrsnetz"}]},"17k":{"marker":"§","title":"Berichterstattung an die Europäische Kommission","referenced_by":[],"references":[{"lawId":"fstrg","section":"17i","marker":"§","title":"Planfeststellungsverfahren bei Vorhaben im transeuropäischen Verkehrsnetz"},{"lawId":"fstrg","section":"17j","marker":"§","title":"Grenzüberschreitende Vorhaben im transeuropäischen Verkehrsnetz"}]},"18f":{"marker":"§","title":"Vorzeitige Besitzeinweisung","referenced_by":[{"lawId":"fstrg","section":"2","marker":"§","title":"Widmung, Umstufung, Einziehung"}],"references":[{"lawId":"fstrg","section":"73","marker":"§","title":null},{"lawId":"fstrg","section":"80","marker":"§","title":null},{"lawId":"fstrg","section":"17f","marker":"§","title":"Anlagen der Verkehrsüberwachung, der Unfallhilfe und des"}]},"19a":{"marker":"§","title":"Entschädigungsverfahren","referenced_by":[],"references":[{"lawId":"fstrg","section":"8a","marker":"§","title":"Straßenanlieger"}]},"23a":{"marker":"§","title":"Gebühren, Verordnungsermächtigung","referenced_by":[{"lawId":"fstrg","section":"24","marker":"§","title":"Übergangs- und Schlussbestimmungen"}],"references":[{"lawId":"fstrg","section":"8","marker":"§","title":"Sondernutzungen; Verordnungsermächtigung"},{"lawId":"fstrg","section":"9","marker":"§","title":"Bauliche Anlagen an Bundesfernstraßen"},{"lawId":"fstrg","section":"22","marker":"§","title":"Zuständigkeit; Verordnungsermächtigung"},{"lawId":"fstrg","section":"8","marker":"§","title":"Sondernutzungen; Verordnungsermächtigung"},{"lawId":"fstrg","section":"9","marker":"§","title":"Bauliche Anlagen an Bundesfernstraßen"},{"lawId":"fstrg","section":"22","marker":"§","title":"Zuständigkeit; Verordnungsermächtigung"}]}}}