{"law_abbr":"UStatG 2005","by_section":{"2":{"marker":"§","title":"Erhebungen, Berichtsjahr","referenced_by":[{"lawId":"ustatg 2005","section":"8","marker":"§","title":"Erhebung der nichtöffentlichen Wasserversorgung und Abwasserentsorgung"},{"lawId":"ustatg 2005","section":"11","marker":"§","title":"Erhebung der Aufwendungen für den Umweltschutz"},{"lawId":"ustatg 2005","section":"11","marker":"§","title":"Erhebung der Aufwendungen für den Umweltschutz"},{"lawId":"ustatg 2005","section":"16","marker":"§","title":"Übermittlung"},{"lawId":"ustatg 2005","section":"16","marker":"§","title":"Übermittlung"}],"references":[]},"3":{"marker":"§","title":"Erhebung der Abfallentsorgung","referenced_by":[{"lawId":"ustatg 2005","section":"5a","marker":"§","title":"Erhebung des Inverkehrbringens und der Entsorgung bestimmter Erzeugnisse"},{"lawId":"ustatg 2005","section":"5a","marker":"§","title":"Erhebung des Inverkehrbringens und der Entsorgung bestimmter Erzeugnisse"},{"lawId":"ustatg 2005","section":"5a","marker":"§","title":"Erhebung des Inverkehrbringens und der Entsorgung bestimmter Erzeugnisse"},{"lawId":"ustatg 2005","section":"5a","marker":"§","title":"Erhebung des Inverkehrbringens und der Entsorgung bestimmter Erzeugnisse"},{"lawId":"ustatg 2005","section":"6","marker":"§","title":"Aufbereitung und Veröffentlichung der abfallstatistischen Erhebungen"},{"lawId":"ustatg 2005","section":"6","marker":"§","title":"Aufbereitung und Veröffentlichung der abfallstatistischen Erhebungen"},{"lawId":"ustatg 2005","section":"11","marker":"§","title":"Erhebung der Aufwendungen für den Umweltschutz"},{"lawId":"ustatg 2005","section":"13","marker":"§","title":"Hilfsmerkmale"},{"lawId":"ustatg 2005","section":"15","marker":"§","title":"Anschriftenübermittlung"},{"lawId":"ustatg 2005","section":"15","marker":"§","title":"Anschriftenübermittlung"},{"lawId":"ustatg 2005","section":"15","marker":"§","title":"Anschriftenübermittlung"},{"lawId":"ustatg 2005","section":"16","marker":"§","title":"Übermittlung"},{"lawId":"ustatg 2005","section":"16","marker":"§","title":"Übermittlung"}],"references":[]},"4":{"marker":"§","title":"Erhebung der Abfälle, über die Nachweise zu führen sind","referenced_by":[{"lawId":"ustatg 2005","section":"16","marker":"§","title":"Übermittlung"}],"references":[]},"5":{"marker":"§","title":"Erhebung der Entsorgung bestimmter Abfälle","referenced_by":[],"references":[{"lawId":"ustatg 2005","section":"15","marker":"§","title":"Anschriftenübermittlung"},{"lawId":"ustatg 2005","section":"31","marker":"§","title":null}]},"6":{"marker":"§","title":"Aufbereitung und Veröffentlichung der abfallstatistischen Erhebungen","referenced_by":[{"lawId":"ustatg 2005","section":"5a","marker":"§","title":"Erhebung des Inverkehrbringens und der Entsorgung bestimmter Erzeugnisse"},{"lawId":"ustatg 2005","section":"11","marker":"§","title":"Erhebung der Aufwendungen für den Umweltschutz"},{"lawId":"ustatg 2005","section":"16","marker":"§","title":"Übermittlung"}],"references":[{"lawId":"ustatg 2005","section":"3","marker":"§","title":"Erhebung der Abfallentsorgung"},{"lawId":"ustatg 2005","section":"3","marker":"§","title":"Erhebung der Abfallentsorgung"}]},"7":{"marker":"§","title":"Erhebung der öffentlichen Wasserversorgung und Abwasserentsorgung","referenced_by":[{"lawId":"ustatg 2005","section":"13","marker":"§","title":"Hilfsmerkmale"},{"lawId":"ustatg 2005","section":"16","marker":"§","title":"Übermittlung"},{"lawId":"ustatg 2005","section":"16","marker":"§","title":"Übermittlung"},{"lawId":"ustatg 2005","section":"16","marker":"§","title":"Übermittlung"}],"references":[]},"8":{"marker":"§","title":"Erhebung der nichtöffentlichen Wasserversorgung und Abwasserentsorgung","referenced_by":[{"lawId":"ustatg 2005","section":"15","marker":"§","title":"Anschriftenübermittlung"}],"references":[{"lawId":"ustatg 2005","section":"2","marker":"§","title":"Erhebungen, Berichtsjahr"}]},"9":{"marker":"§","title":"Erhebung der Unfälle beim Umgang mit und bei der Beförderung von wassergefährdenden Stoffen","referenced_by":[{"lawId":"ustatg 2005","section":"15","marker":"§","title":"Anschriftenübermittlung"},{"lawId":"ustatg 2005","section":"18","marker":"§","title":"Übergangsregelung"},{"lawId":"ustatg 2005","section":"18","marker":"§","title":"Übergangsregelung"}],"references":[]},"11":{"marker":"§","title":"Erhebung der Aufwendungen für den Umweltschutz","referenced_by":[{"lawId":"ustatg 2005","section":"14","marker":"§","title":"Auskunftspflicht"},{"lawId":"ustatg 2005","section":"16","marker":"§","title":"Übermittlung"}],"references":[{"lawId":"ustatg 2005","section":"2","marker":"§","title":"Erhebungen, Berichtsjahr"},{"lawId":"ustatg 2005","section":"3","marker":"§","title":"Erhebung der Abfallentsorgung"},{"lawId":"ustatg 2005","section":"6","marker":"§","title":"Aufbereitung und Veröffentlichung der abfallstatistischen Erhebungen"},{"lawId":"ustatg 2005","section":"6a","marker":"§","title":null},{"lawId":"ustatg 2005","section":"2","marker":"§","title":"Erhebungen, Berichtsjahr"}]},"12":{"marker":"§","title":"Erhebung der Güter und Leistungen für den Umweltschutz","referenced_by":[{"lawId":"ustatg 2005","section":"16","marker":"§","title":"Übermittlung"}],"references":[]},"13":{"marker":"§","title":"Hilfsmerkmale","referenced_by":[{"lawId":"ustatg 2005","section":"14","marker":"§","title":"Auskunftspflicht"},{"lawId":"ustatg 2005","section":"18","marker":"§","title":"Übergangsregelung"}],"references":[{"lawId":"ustatg 2005","section":"3","marker":"§","title":"Erhebung der Abfallentsorgung"},{"lawId":"ustatg 2005","section":"7","marker":"§","title":"Erhebung der öffentlichen Wasserversorgung und Abwasserentsorgung"}]},"14":{"marker":"§","title":"Auskunftspflicht","referenced_by":[],"references":[{"lawId":"ustatg 2005","section":"13","marker":"§","title":"Hilfsmerkmale"},{"lawId":"ustatg 2005","section":"11","marker":"§","title":"Erhebung der Aufwendungen für den Umweltschutz"}]},"15":{"marker":"§","title":"Anschriftenübermittlung","referenced_by":[{"lawId":"ustatg 2005","section":"5","marker":"§","title":"Erhebung der Entsorgung bestimmter Abfälle"}],"references":[{"lawId":"ustatg 2005","section":"3","marker":"§","title":"Erhebung der Abfallentsorgung"},{"lawId":"ustatg 2005","section":"3","marker":"§","title":"Erhebung der Abfallentsorgung"},{"lawId":"ustatg 2005","section":"31","marker":"§","title":null},{"lawId":"ustatg 2005","section":"5a","marker":"§","title":"Erhebung des Inverkehrbringens und der Entsorgung bestimmter Erzeugnisse"},{"lawId":"ustatg 2005","section":"3","marker":"§","title":"Erhebung der Abfallentsorgung"},{"lawId":"ustatg 2005","section":"5a","marker":"§","title":"Erhebung des Inverkehrbringens und der Entsorgung bestimmter Erzeugnisse"},{"lawId":"ustatg 2005","section":"8","marker":"§","title":"Erhebung der nichtöffentlichen Wasserversorgung und Abwasserentsorgung"},{"lawId":"ustatg 2005","section":"9","marker":"§","title":"Erhebung der Unfälle beim Umgang mit und bei der Beförderung von wassergefährdenden Stoffen"}]},"16":{"marker":"§","title":"Übermittlung","referenced_by":[],"references":[{"lawId":"ustatg 2005","section":"3","marker":"§","title":"Erhebung der Abfallentsorgung"},{"lawId":"ustatg 2005","section":"7","marker":"§","title":"Erhebung der öffentlichen Wasserversorgung und Abwasserentsorgung"},{"lawId":"ustatg 2005","section":"2","marker":"§","title":"Erhebungen, Berichtsjahr"},{"lawId":"ustatg 2005","section":"3","marker":"§","title":"Erhebung der Abfallentsorgung"},{"lawId":"ustatg 2005","section":"6","marker":"§","title":"Aufbereitung und Veröffentlichung der abfallstatistischen Erhebungen"},{"lawId":"ustatg 2005","section":"6a","marker":"§","title":null},{"lawId":"ustatg 2005","section":"7","marker":"§","title":"Erhebung der öffentlichen Wasserversorgung und Abwasserentsorgung"},{"lawId":"ustatg 2005","section":"11","marker":"§","title":"Erhebung der Aufwendungen für den Umweltschutz"},{"lawId":"ustatg 2005","section":"2","marker":"§","title":"Erhebungen, Berichtsjahr"},{"lawId":"ustatg 2005","section":"4","marker":"§","title":"Erhebung der Abfälle, über die Nachweise zu führen sind"},{"lawId":"ustatg 2005","section":"7","marker":"§","title":"Erhebung der öffentlichen Wasserversorgung und Abwasserentsorgung"},{"lawId":"ustatg 2005","section":"12","marker":"§","title":"Erhebung der Güter und Leistungen für den Umweltschutz"}]},"18":{"marker":"§","title":"Übergangsregelung","referenced_by":[],"references":[{"lawId":"ustatg 2005","section":"9","marker":"§","title":"Erhebung der Unfälle beim Umgang mit und bei der Beförderung von wassergefährdenden Stoffen"},{"lawId":"ustatg 2005","section":"9","marker":"§","title":"Erhebung der Unfälle beim Umgang mit und bei der Beförderung von wassergefährdenden Stoffen"},{"lawId":"ustatg 2005","section":"13","marker":"§","title":"Hilfsmerkmale"}]},"5a":{"marker":"§","title":"Erhebung des Inverkehrbringens und der Entsorgung bestimmter Erzeugnisse","referenced_by":[{"lawId":"ustatg 2005","section":"15","marker":"§","title":"Anschriftenübermittlung"},{"lawId":"ustatg 2005","section":"15","marker":"§","title":"Anschriftenübermittlung"}],"references":[{"lawId":"ustatg 2005","section":"3","marker":"§","title":"Erhebung der Abfallentsorgung"},{"lawId":"ustatg 2005","section":"3","marker":"§","title":"Erhebung der Abfallentsorgung"},{"lawId":"ustatg 2005","section":"3","marker":"§","title":"Erhebung der Abfallentsorgung"},{"lawId":"ustatg 2005","section":"3","marker":"§","title":"Erhebung der Abfallentsorgung"},{"lawId":"ustatg 2005","section":"6","marker":"§","title":"Aufbereitung und Veröffentlichung der abfallstatistischen Erhebungen"}]}}}