{"law_abbr":"WeinFöGewV","by_section":{"1":{"marker":"§","title":"Anwendungsbereich und Gegenstand","referenced_by":[{"lawId":"weinfögewv","section":"2","marker":"§","title":"Begünstigte"},{"lawId":"weinfögewv","section":"2","marker":"§","title":"Begünstigte"},{"lawId":"weinfögewv","section":"2","marker":"§","title":"Begünstigte"},{"lawId":"weinfögewv","section":"2","marker":"§","title":"Begünstigte"},{"lawId":"weinfögewv","section":"2","marker":"§","title":"Begünstigte"},{"lawId":"weinfögewv","section":"2","marker":"§","title":"Begünstigte"},{"lawId":"weinfögewv","section":"3","marker":"§","title":"Zuständige Stellen"},{"lawId":"weinfögewv","section":"3","marker":"§","title":"Zuständige Stellen"},{"lawId":"weinfögewv","section":"3","marker":"§","title":"Zuständige Stellen"},{"lawId":"weinfögewv","section":"4","marker":"§","title":"Antragsverfahren"},{"lawId":"weinfögewv","section":"4","marker":"§","title":"Antragsverfahren"},{"lawId":"weinfögewv","section":"4","marker":"§","title":"Antragsverfahren"},{"lawId":"weinfögewv","section":"4","marker":"§","title":"Antragsverfahren"},{"lawId":"weinfögewv","section":"5","marker":"§","title":"(doppelt)"},{"lawId":"weinfögewv","section":"5","marker":"§","title":"(doppelt)"},{"lawId":"weinfögewv","section":"5","marker":"§","title":"(doppelt)"},{"lawId":"weinfögewv","section":"5","marker":"§","title":"(doppelt)"},{"lawId":"weinfögewv","section":"5","marker":"§","title":"(doppelt)"},{"lawId":"weinfögewv","section":"8","marker":"§","title":"Förderfähigkeit von maßnahmenbezogenen Kosten"},{"lawId":"weinfögewv","section":"8","marker":"§","title":"Förderfähigkeit von maßnahmenbezogenen Kosten"},{"lawId":"weinfögewv","section":"8","marker":"§","title":"Förderfähigkeit von maßnahmenbezogenen Kosten"},{"lawId":"weinfögewv","section":"8","marker":"§","title":"Förderfähigkeit von maßnahmenbezogenen Kosten"},{"lawId":"weinfögewv","section":"8","marker":"§","title":"Förderfähigkeit von maßnahmenbezogenen Kosten"},{"lawId":"weinfögewv","section":"8","marker":"§","title":"Förderfähigkeit von maßnahmenbezogenen Kosten"},{"lawId":"weinfögewv","section":"9","marker":"§","title":"Förderfähigkeit von Personalkosten"},{"lawId":"weinfögewv","section":"10","marker":"§","title":"Förderfähigkeit von Verwaltungskosten"},{"lawId":"weinfögewv","section":"12","marker":"§","title":"Mindestparzellengröße bei der Umstrukturierung und Umstellung von Rebflächen"},{"lawId":"weinfögewv","section":"13","marker":"§","title":"Zweckbindungsfrist"},{"lawId":"weinfögewv","section":"13","marker":"§","title":"Zweckbindungsfrist"},{"lawId":"weinfögewv","section":"14","marker":"§","title":"Dauer der Förderung"},{"lawId":"weinfögewv","section":"14","marker":"§","title":"Dauer der Förderung"},{"lawId":"weinfögewv","section":"14","marker":"§","title":"Dauer der Förderung"},{"lawId":"weinfögewv","section":"18","marker":"§","title":"Mitteilungspflichten"},{"lawId":"weinfögewv","section":"20","marker":"§","title":"Verwaltungskontrollen"},{"lawId":"weinfögewv","section":"21","marker":"§","title":"Inhalt der Vor-Ort-Kontrollen"},{"lawId":"weinfögewv","section":"23","marker":"§","title":"Kontrollsatz und Stichprobenerhebung für Vor-Ort-Kontrollen"},{"lawId":"weinfögewv","section":"25","marker":"§","title":"Verwaltungs- und Vor-Ort-Kontrollen bei Umstrukturierung und Umstellung von Rebflächen"},{"lawId":"weinfögewv","section":"27","marker":"§","title":"Berichte über Vor-Ort-Kontrollen"}],"references":[]},"2":{"marker":"§","title":"Begünstigte","referenced_by":[],"references":[{"lawId":"weinfögewv","section":"1","marker":"§","title":"Anwendungsbereich und Gegenstand"},{"lawId":"weinfögewv","section":"1","marker":"§","title":"Anwendungsbereich und Gegenstand"},{"lawId":"weinfögewv","section":"1","marker":"§","title":"Anwendungsbereich und Gegenstand"},{"lawId":"weinfögewv","section":"1","marker":"§","title":"Anwendungsbereich und Gegenstand"},{"lawId":"weinfögewv","section":"1","marker":"§","title":"Anwendungsbereich und Gegenstand"},{"lawId":"weinfögewv","section":"1","marker":"§","title":"Anwendungsbereich und Gegenstand"}]},"3":{"marker":"§","title":"Zuständige Stellen","referenced_by":[],"references":[{"lawId":"weinfögewv","section":"1","marker":"§","title":"Anwendungsbereich und Gegenstand"},{"lawId":"weinfögewv","section":"1","marker":"§","title":"Anwendungsbereich und Gegenstand"},{"lawId":"weinfögewv","section":"1","marker":"§","title":"Anwendungsbereich und Gegenstand"}]},"4":{"marker":"§","title":"Antragsverfahren","referenced_by":[],"references":[{"lawId":"weinfögewv","section":"1","marker":"§","title":"Anwendungsbereich und Gegenstand"},{"lawId":"weinfögewv","section":"5","marker":"§","title":"(doppelt)"},{"lawId":"weinfögewv","section":"1","marker":"§","title":"Anwendungsbereich und Gegenstand"},{"lawId":"weinfögewv","section":"1","marker":"§","title":"Anwendungsbereich und Gegenstand"},{"lawId":"weinfögewv","section":"1","marker":"§","title":"Anwendungsbereich und Gegenstand"}]},"5":{"marker":"§","title":"(doppelt)","referenced_by":[{"lawId":"weinfögewv","section":"4","marker":"§","title":"Antragsverfahren"}],"references":[{"lawId":"weinfögewv","section":"1","marker":"§","title":"Anwendungsbereich und Gegenstand"},{"lawId":"weinfögewv","section":"1","marker":"§","title":"Anwendungsbereich und Gegenstand"},{"lawId":"weinfögewv","section":"1","marker":"§","title":"Anwendungsbereich und Gegenstand"},{"lawId":"weinfögewv","section":"1","marker":"§","title":"Anwendungsbereich und Gegenstand"},{"lawId":"weinfögewv","section":"1","marker":"§","title":"Anwendungsbereich und Gegenstand"}]},"8":{"marker":"§","title":"Förderfähigkeit von maßnahmenbezogenen Kosten","referenced_by":[],"references":[{"lawId":"weinfögewv","section":"1","marker":"§","title":"Anwendungsbereich und Gegenstand"},{"lawId":"weinfögewv","section":"1","marker":"§","title":"Anwendungsbereich und Gegenstand"},{"lawId":"weinfögewv","section":"1","marker":"§","title":"Anwendungsbereich und Gegenstand"},{"lawId":"weinfögewv","section":"1","marker":"§","title":"Anwendungsbereich und Gegenstand"},{"lawId":"weinfögewv","section":"1","marker":"§","title":"Anwendungsbereich und Gegenstand"},{"lawId":"weinfögewv","section":"1","marker":"§","title":"Anwendungsbereich und Gegenstand"}]},"9":{"marker":"§","title":"Förderfähigkeit von Personalkosten","referenced_by":[],"references":[{"lawId":"weinfögewv","section":"1","marker":"§","title":"Anwendungsbereich und Gegenstand"}]},"10":{"marker":"§","title":"Förderfähigkeit von Verwaltungskosten","referenced_by":[],"references":[{"lawId":"weinfögewv","section":"1","marker":"§","title":"Anwendungsbereich und Gegenstand"}]},"11":{"marker":"§","title":"Förderfähigkeit der Umsatzsteuer","referenced_by":[],"references":[{"lawId":"weinfögewv","section":"2b","marker":"§","title":null}]},"12":{"marker":"§","title":"Mindestparzellengröße bei der Umstrukturierung und Umstellung von Rebflächen","referenced_by":[],"references":[{"lawId":"weinfögewv","section":"1","marker":"§","title":"Anwendungsbereich und Gegenstand"}]},"13":{"marker":"§","title":"Zweckbindungsfrist","referenced_by":[],"references":[{"lawId":"weinfögewv","section":"1","marker":"§","title":"Anwendungsbereich und Gegenstand"},{"lawId":"weinfögewv","section":"1","marker":"§","title":"Anwendungsbereich und Gegenstand"}]},"14":{"marker":"§","title":"Dauer der Förderung","referenced_by":[],"references":[{"lawId":"weinfögewv","section":"1","marker":"§","title":"Anwendungsbereich und Gegenstand"},{"lawId":"weinfögewv","section":"1","marker":"§","title":"Anwendungsbereich und Gegenstand"},{"lawId":"weinfögewv","section":"1","marker":"§","title":"Anwendungsbereich und Gegenstand"}]},"18":{"marker":"§","title":"Mitteilungspflichten","referenced_by":[],"references":[{"lawId":"weinfögewv","section":"1","marker":"§","title":"Anwendungsbereich und Gegenstand"}]},"20":{"marker":"§","title":"Verwaltungskontrollen","referenced_by":[],"references":[{"lawId":"weinfögewv","section":"1","marker":"§","title":"Anwendungsbereich und Gegenstand"}]},"21":{"marker":"§","title":"Inhalt der Vor-Ort-Kontrollen","referenced_by":[],"references":[{"lawId":"weinfögewv","section":"1","marker":"§","title":"Anwendungsbereich und Gegenstand"}]},"23":{"marker":"§","title":"Kontrollsatz und Stichprobenerhebung für Vor-Ort-Kontrollen","referenced_by":[],"references":[{"lawId":"weinfögewv","section":"1","marker":"§","title":"Anwendungsbereich und Gegenstand"}]},"25":{"marker":"§","title":"Verwaltungs- und Vor-Ort-Kontrollen bei Umstrukturierung und Umstellung von Rebflächen","referenced_by":[],"references":[{"lawId":"weinfögewv","section":"1","marker":"§","title":"Anwendungsbereich und Gegenstand"}]},"27":{"marker":"§","title":"Berichte über Vor-Ort-Kontrollen","referenced_by":[],"references":[{"lawId":"weinfögewv","section":"1","marker":"§","title":"Anwendungsbereich und Gegenstand"}]}}}